beakeredis/__init__.py
beakeredis-0.1.0.dist-info/DESCRIPTION.rst
beakeredis-0.1.0.dist-info/METADATA
beakeredis-0.1.0.dist-info/RECORD
beakeredis-0.1.0.dist-info/WHEEL
beakeredis-0.1.0.dist-info/entry_points.txt
beakeredis-0.1.0.dist-info/metadata.json
beakeredis-0.1.0.dist-info/top_level.txt
