Metadata-Version: 2.0
Name: beakeredis
Version: 0.1.0
Summary: Redis backend for Beaker
Home-page: https://github.com/aspyatkin/beakeredis
Author: Alexander Pyatkin
Author-email: asp@thexyz.net
License: MIT
Keywords: Beaker
Platform: UNKNOWN
Classifier: Development Status :: 4 - Beta
Classifier: Intended Audience :: Developers
Classifier: License :: OSI Approved :: MIT License
Classifier: Operating System :: OS Independent
Classifier: Programming Language :: Python
Classifier: Programming Language :: Python :: 2
Classifier: Programming Language :: Python :: 2.6
Classifier: Programming Language :: Python :: 2.7
Classifier: Programming Language :: Python :: 3
Classifier: Programming Language :: Python :: 3.3
Classifier: Programming Language :: Python :: 3.4
Classifier: Programming Language :: Python :: 3.5
Classifier: Programming Language :: Python :: Implementation :: CPython
Classifier: Topic :: Utilities
Requires-Dist: Beaker (>=1.6.4)
Requires-Dist: redis (>=2.10)
